dynamics/__init__.py
dynamics/contacts.py
dynamics/dynamics.py
dynamicscontacts-0.8.0.dist-info/LICENSE.txt
dynamicscontacts-0.8.0.dist-info/METADATA
dynamicscontacts-0.8.0.dist-info/WHEEL
dynamicscontacts-0.8.0.dist-info/top_level.txt
dynamicscontacts-0.8.0.dist-info/RECORD
