Metadata-Version: 2.1
Name: dynamicscontacts
Version: 0.8.0
Summary: This library provides developers with a simplified way to authenticate, search contact, add contact, update contact, and delete contact in Dynamics Customer Insights - Journeys 
Home-page: https://github.com/mabusalah/Dynamics
Author: Dr. Mustafa Abusalah
Author-email: muabusalah@gmail.com
Classifier: Programming Language :: Python :: 3
Classifier: License :: OSI Approved :: Apache Software License
Classifier: Operating System :: OS Independent
Requires-Python: >=3.6
License-File: LICENSE.txt
Requires-Dist: requests
